orc_client/__init__.py
orc_client/cli.py
orc_client/client.py
orchestracto_client-0.9.0.dist-info/METADATA
orchestracto_client-0.9.0.dist-info/WHEEL
orchestracto_client-0.9.0.dist-info/entry_points.txt
orchestracto_client-0.9.0.dist-info/top_level.txt
orchestracto_client-0.9.0.dist-info/RECORD
