Metadata-Version: 2.4
Name: orchestracto-client
Version: 0.9.0
Author: TractoAI team
Requires-Python: >=3.10
Requires-Dist: PyYAML~=6.0.2
Requires-Dist: requests~=2.32.3
